{
  "QBXML": {
    "QBXMLMsgsRq": {
      "@onError": "stopOnError",
      "ItemOtherChargeModRq": {
        "ItemOtherChargeMod": {
          "ListID": "IDTYPE",
          "EditSequence": "STRTYPE",
          "Name": "STRTYPE",
          "BarCode": {
            "BarCodeValue": "STRTYPE",
            "AssignEvenIfUsed": "BOOLTYPE",
            "AllowOverride": "BOOLTYPE"
          },
          "IsActive": "BOOLTYPE",
          "ClassRef": {
            "ListID": "IDTYPE",
            "FullName": "STRTYPE"
          },
          "ParentRef": {
            "ListID": "IDTYPE",
            "FullName": "STRTYPE"
          },
          "IsTaxIncluded": "BOOLTYPE",
          "SalesTaxCodeRef": {
            "ListID": "IDTYPE",
            "FullName": "STRTYPE"
          },
          "SalesOrPurchaseMod": {
            "Desc": "STRTYPE",
            "Price": "PRICETYPE",
            "PricePercent": "PERCENTTYPE",
            "AccountRef": {
              "ListID": "IDTYPE",
              "FullName": "STRTYPE"
            },
            "ApplyAccountRefToExistingTxns": "BOOLTYPE"
          },
          "SalesAndPurchaseMod": {
            "SalesDesc": "STRTYPE",
            "SalesPrice": "PRICETYPE",
            "IncomeAccountRef": {
              "ListID": "IDTYPE",
              "FullName": "STRTYPE"
            },
            "ApplyIncomeAccountRefToExistingTxns": "BOOLTYPE",
            "PurchaseDesc": "STRTYPE",
            "PurchaseCost": "PRICETYPE",
            "PurchaseTaxCodeRef": {
              "ListID": "IDTYPE",
              "FullName": "STRTYPE"
            },
            "ExpenseAccountRef": {
              "ListID": "IDTYPE",
              "FullName": "STRTYPE"
            },
            "ApplyExpenseAccountRefToExistingTxns": "BOOLTYPE",
            "PrefVendorRef": {
              "ListID": "IDTYPE",
              "FullName": "STRTYPE"
            }
          }
        },
        "IncludeRetElement": "STRTYPE"
      },
      "ItemOtherChargeModRs": {
        "@statusCode": "INTTYPE",
        "@statusMessage": "STRTYPE",
        "@statusSeverity": "STRTYPE",
        "ItemOtherChargeRet": {
          "ListID": "IDTYPE",
          "TimeCreated": "DATETIMETYPE",
          "TimeModified": "DATETIMETYPE",
          "EditSequence": "STRTYPE",
          "Name": "STRTYPE",
          "FullName": "STRTYPE",
          "BarCodeValue": "STRTYPE",
          "IsActive": "BOOLTYPE",
          "ClassRef": {
            "ListID": "IDTYPE",
            "FullName": "STRTYPE"
          },
          "ParentRef": {
            "ListID": "IDTYPE",
            "FullName": "STRTYPE"
          },
          "Sublevel": "INTTYPE",
          "IsTaxIncluded": "BOOLTYPE",
          "SalesTaxCodeRef": {
            "ListID": "IDTYPE",
            "FullName": "STRTYPE"
          },
          "SalesOrPurchase": {
            "Desc": "STRTYPE",
            "Price": "PRICETYPE",
            "PricePercent": "PERCENTTYPE",
            "AccountRef": {
              "ListID": "IDTYPE",
              "FullName": "STRTYPE"
            }
          },
          "SalesAndPurchase": {
            "SalesDesc": "STRTYPE",
            "SalesPrice": "PRICETYPE",
            "IncomeAccountRef": {
              "ListID": "IDTYPE",
              "FullName": "STRTYPE"
            },
            "PurchaseDesc": "STRTYPE",
            "PurchaseCost": "PRICETYPE",
            "PurchaseTaxCodeRef": {
              "ListID": "IDTYPE",
              "FullName": "STRTYPE"
            },
            "ExpenseAccountRef": {
              "ListID": "IDTYPE",
              "FullName": "STRTYPE"
            },
            "PrefVendorRef": {
              "ListID": "IDTYPE",
              "FullName": "STRTYPE"
            }
          },
          "SpecialItemType": "ENUMTYPE",
          "ExternalGUID": "GUIDTYPE",
          "DataExtRet": {
            "OwnerID": "GUIDTYPE",
            "DataExtName": "STRTYPE",
            "DataExtType": "ENUMTYPE",
            "DataExtValue": "STRTYPE"
          }
        },
        "ErrorRecovery": {
          "ListID": "IDTYPE",
          "OwnerID": "GUIDTYPE",
          "TxnID": "IDTYPE",
          "TxnNumber": "INTTYPE",
          "EditSequence": "STRTYPE",
          "ExternalGUID": "GUIDTYPE"
        }
      }
    }
  }
}