{
  "QBXMLMsgsRq": {
    "TransferAddRq": {
      "TransferAdd": {
        "@optional": false,
        "@required": true,
        "@may_repeat": false,
        "TxnDate": {
          "@optional": true,
          "@required": false,
          "@may_repeat": false
        },
        "TransferFromAccountRef": {
          "@optional": true,
          "@required": false,
          "@may_repeat": false,
          "ListID": {
            "@optional": true,
            "@required": false,
            "@may_repeat": false
          },
          "FullName": {
            "@optional": true,
            "@required": false,
            "@may_repeat": false
          }
        },
        "TransferToAccountRef": {
          "@optional": true,
          "@required": false,
          "@may_repeat": false,
          "ListID": {
            "@optional": true,
            "@required": false,
            "@may_repeat": false
          },
          "FullName": {
            "@optional": true,
            "@required": false,
            "@may_repeat": false
          }
        },
        "ClassRef": {
          "@optional": true,
          "@required": false,
          "@may_repeat": false,
          "ListID": {
            "@optional": true,
            "@required": false,
            "@may_repeat": false
          },
          "FullName": {
            "@optional": true,
            "@required": false,
            "@may_repeat": false
          }
        },
        "Amount": {
          "@optional": true,
          "@required": false,
          "@may_repeat": false
        },
        "Memo": {
          "@optional": true,
          "@required": false,
          "@may_repeat": false
        }
      },
      "IncludeRetElement": {
        "@optional": true,
        "@required": false,
        "@may_repeat": true
      }
    },
    "TransferAddRs": {
      "TransferRet": {
        "@optional": true,
        "@required": false,
        "@may_repeat": false,
        "TxnID": {
          "@optional": false,
          "@required": true,
          "@may_repeat": false
        },
        "TimeCreated": {
          "@optional": false,
          "@required": true,
          "@may_repeat": false
        },
        "TimeModified": {
          "@optional": false,
          "@required": true,
          "@may_repeat": false
        },
        "EditSequence": {
          "@optional": false,
          "@required": true,
          "@may_repeat": false
        },
        "TxnNumber": {
          "@optional": true,
          "@required": false,
          "@may_repeat": false
        },
        "TxnDate": {
          "@optional": true,
          "@required": false,
          "@may_repeat": false
        },
        "TransferFromAccountRef": {
          "@optional": true,
          "@required": false,
          "@may_repeat": false,
          "ListID": {
            "@optional": true,
            "@required": false,
            "@may_repeat": false
          },
          "FullName": {
            "@optional": true,
            "@required": false,
            "@may_repeat": false
          }
        },
        "FromAccountBalance": {
          "@optional": true,
          "@required": false,
          "@may_repeat": false
        },
        "TransferToAccountRef": {
          "@optional": true,
          "@required": false,
          "@may_repeat": false,
          "ListID": {
            "@optional": true,
            "@required": false,
            "@may_repeat": false
          },
          "FullName": {
            "@optional": true,
            "@required": false,
            "@may_repeat": false
          }
        },
        "ToAccountBalance": {
          "@optional": true,
          "@required": false,
          "@may_repeat": false
        },
        "ClassRef": {
          "@optional": true,
          "@required": false,
          "@may_repeat": false,
          "ListID": {
            "@optional": true,
            "@required": false,
            "@may_repeat": false
          },
          "FullName": {
            "@optional": true,
            "@required": false,
            "@may_repeat": false
          }
        },
        "Amount": {
          "@optional": true,
          "@required": false,
          "@may_repeat": false
        },
        "Memo": {
          "@optional": true,
          "@required": false,
          "@may_repeat": false
        }
      }
    }
  }
}